pax8/__init__.py
pax8/__version__.py
pax8/enums.py
pax8/exceptions.py
pax8/filters.py
pax8/rest.py
pax8/types.py
pax8-0.5.dist-info/LICENSE
pax8-0.5.dist-info/METADATA
pax8-0.5.dist-info/WHEEL
pax8-0.5.dist-info/top_level.txt
pax8-0.5.dist-info/zip-safe
pax8-0.5.dist-info/RECORD
