Metadata-Version: 2.1
Name: pax8
Version: 0.5
Summary: Python package for API requests to the Pax8 partner API
Home-page: https://github.com/scheibling/pax8
Author: Lars Scheibling
Author-email: lars@scheibling.se
License: GnuPG 3.0
Keywords: python pax pax8 partner api
Classifier: Programming Language :: Python :: 3
Classifier: License :: OSI Approved :: GNU General Public License v3 (GPLv3)
Classifier: Operating System :: OS Independent
Requires-Python: >=3.6
License-File: LICENSE
Requires-Dist: click
Requires-Dist: cprint
Requires-Dist: requests
